{
    "hero": {
        "badge": "Contact Us",
        "title": "Contacts",
        "subtitle": "Submit a request — we'll respond within 2 hours"
    },
    "address": {
        "city": "Moscow",
        "street": "Logisticheskaya St., 1",
        "postal": "123456"
    },
    "phone": "+7 (495) 000-00-00",
    "email": "info@resurs.ru",
    "workingHours": {
        "weekdays": "Mon–Fri: 9:00 AM – 8:00 PM",
        "weekends": "Sat–Sun: By appointment"
    },
    "formTitle": "Submit Request",
    "formSubtitle": "Describe your task — we'll prepare a personalized offer"
}
